.autodocstring.mustache
.coveragerc
.flake8
.gitignore
.pre-commit-config.yaml
.readthedocs.yml
LICENSE.txt
Makefile
README.md
mkdocs.yml
requirements.dev.txt
requirements.txt
setup.cfg
setup.py
setup.sh
.github/workflows/main.yml
docs/README.md
docs/advanced_usage.ipynb
docs/setup.py
docs/tutorial.ipynb
docs/assets/coverage.svg
docs/assets/framework.png
docs/overrides/main.html
docs/reference/common.md
docs/reference/convert.md
docs/reference/fuse.md
docs/reference/imitation.md
docs/reference/quantize.md
docs/reference/sparse.md
docs/reference/util.md
examples/.gitkeep
examples/README.md
examples/mnist.py
qsparse/__init__.py
qsparse/common.py
qsparse/convert.py
qsparse/fuse.py
qsparse/imitation.py
qsparse/quantize.py
qsparse/sparse.py
qsparse/util.py
qsparse.egg-info/PKG-INFO
qsparse.egg-info/SOURCES.txt
qsparse.egg-info/dependency_links.txt
qsparse.egg-info/entry_points.txt
qsparse.egg-info/requires.txt
qsparse.egg-info/top_level.txt
tests/__init__.py
tests/test_convert.py
tests/test_fuse.py
tests/test_quantize.py
tests/test_sparse.py
tests/test_util.py