Metadata-Version: 2.1
Name: qsparse
Version: 2.0.0
Summary: train neural networks with joint quantization and pruning on both weights and activations using any pytorch modules
Home-page: https://qsparse.readthedocs.io/
Author: Xinyu Zhang, Ian Colbert, Srinjoy Das, Ken Kreutz-Delgado
Author-email: xiz368@eng.ucsd.edu
License: UNKNOWN
Download-URL: https://github.com/mlzxy/qsparse/tags
Keywords: pytorch,quantization,pruning,model compression,neural network,machine learning
Platform: UNKNOWN
Requires-Python: >=3.6
